README.md
setup.py
yaat/__init__.py
yaat/app.py
yaat/background.py
yaat/components.py
yaat/concurrency.py
yaat/constants.py
yaat/exceptions.py
yaat/parsers.py
yaat/requests.py
yaat/responses.py
yaat/routing.py
yaat/staticfiles.py
yaat/templating.py
yaat/typing.py
yaat/websockets.py
yaat.egg-info/PKG-INFO
yaat.egg-info/SOURCES.txt
yaat.egg-info/dependency_links.txt
yaat.egg-info/requires.txt
yaat.egg-info/top_level.txt
yaat/middleware/__init__.py
yaat/middleware/base.py
yaat/middleware/cors.py
yaat/middleware/exception.py
yaat/middleware/lifespan.py
yaat/openapi/__init__.py
yaat/openapi/schemas.py
yaat/openapi/swagger.py