Metadata-Version: 2.1
Name: yaat
Version: 0.1.10
Summary: Yet another ASGI toolkit
Home-page: https://github.com/yaat-project/yaat
Author: Khant
Author-email: contact@khant.dev
License: LGPL
Download-URL: https://github.com/yaat-project/yaat/releases/download/v0.1.10/yaat-0.1.10.tar.gz
Keywords: asynchronous,web framework
Platform: UNKNOWN
Classifier: Development Status :: 3 - Alpha
Classifier: Intended Audience :: Developers
Classifier: Topic :: Software Development :: Build Tools
Classifier: License :: OSI Approved :: GNU Lesser General Public License v3 (LGPLv3)
Classifier: Programming Language :: Python :: 3.6
Classifier: Programming Language :: Python :: 3.7
Classifier: Programming Language :: Python :: 3.8
Requires-Python: >=3.6
